{
    "ticker": "NVDA",
    "snapshot_date": "2026-03-31T11:07:24.044471",
    "company_profile": {
        "name": "NVIDIA Corporation",
        "sector": "Technology",
        "industry": "Semiconductors",
        "website": "https://www.nvidia.com",
        "market_cap": 4014456963072,
        "description": "NVIDIA Corporation operates as a data center scale AI infrastructure company. The company operates through two segments, Compute & Networking, and Graphics segments. The Compute & Networking segment provides data center accelerated computing and networking platforms and artificial intelligence solutions and software, and automotive platforms and autonomous and electric vehicle solutions, including software. The Graphics segment offers GeForce GPUs for gaming and PCs; Quadro/NVIDIA RTX GPUs for enterprise workstation graphics. The company's products are used in gaming, professional visualization, data center, and automotive markets. The company sells its products to original equipment manufacturers, original device manufacturers, system integrators and distributors, independent software vendors, cloud service providers, add-in board manufacturers, distributors, automotive manufacturers and tier-1 automotive suppliers, and other ecosystem participants worldwide. It has a collaboration with Tech Mahindra Limited to develop artificial intelligence powered telco network operations reasoning agent. The company has a strategic partnership with Lumentum Holdings Inc. to develop optics technologies for AI and data centers. It also has a strategic partnership with Nebius Group N.V. to develop and deploy hyperscale cloud for the artificial intelligence market. NVIDIA Corporation was incorporated in 1993 and is headquartered in Santa Clara, California.",
        "logo_url": null,
        "Category": null,
        "Book Value": 6.472,
        "Show Profile": false,
        "Change From Previous Close": -1.40282,
        "Profit after Tax": 0,
        "change percent": 0,
        "Last Traded Price": 165.17
    },
    "fundamentals": {
        "pe_ratio": 33.63951,
        "eps": 4.91,
        "revenue": 215938007040,
        "debt": 11411999744,
        "market_cap": 4014456963072,
        "revenue_growth": 73.2,
        "price_change_1y": 52.434884197108126
    },
    "historical_prices": [
        {
            "date": "2025-03-31",
            "open": 105.10522740758995,
            "high": 110.9338556226425,
            "low": 103.6255803841977,
            "close": 108.35446166992188,
            "volume": 299212700
        },
        {
            "date": "2025-04-01",
            "open": 108.49443304563391,
            "high": 110.17403760023085,
            "low": 106.4449205320371,
            "close": 110.12405395507812,
            "volume": 222614000
        },
        {
            "date": "2025-04-02",
            "open": 107.26472214391917,
            "high": 111.95361956622256,
            "low": 106.76483994973236,
            "close": 110.39398193359375,
            "volume": 220601200
        },
        {
            "date": "2025-04-03",
            "open": 103.48562015563714,
            "high": 105.60511590388697,
            "low": 101.57606639857329,
            "close": 101.7760238647461,
            "volume": 338769400
        },
        {
            "date": "2025-04-04",
            "open": 98.88670323249266,
            "high": 100.10640942744341,
            "low": 92.08830207120735,
            "close": 94.28778076171875,
            "volume": 532273800
        },
        {
            "date": "2025-04-07",
            "open": 87.43938789235719,
            "high": 101.72602116602216,
            "low": 86.59958951154498,
            "close": 97.61698913574219,
            "volume": 611041300
        },
        {
            "date": "2025-04-08",
            "open": 103.78553826456235,
            "high": 105.82505852328022,
            "low": 94.43774279946976,
            "close": 96.27731323242188,
            "volume": 476243400
        },
        {
            "date": "2025-04-09",
            "open": 98.86669810018236,
            "high": 115.07287764897656,
            "low": 97.5070179445592,
            "close": 114.30306243896484,
            "volume": 612918300
        },
        {
            "date": "2025-04-10",
            "open": 109.34423379452805,
            "high": 110.83388059600858,
            "low": 99.12664053501021,
            "close": 107.5446548461914,
            "volume": 437812400
        },
        {
            "date": "2025-04-11",
            "open": 108.47443427245335,
            "high": 111.52371865557488,
            "low": 107.45467796999777,
            "close": 110.90386199951172,
            "volume": 313417300
        },
        {
            "date": "2025-04-14",
            "open": 114.08311462021162,
            "high": 114.2630725146749,
            "low": 109.04430120283689,
            "close": 110.68391418457031,
            "volume": 264705000
        },
        {
            "date": "2025-04-15",
            "open": 110.94385517244878,
            "high": 113.5932323217664,
            "low": 110.47396469045397,
            "close": 112.1735610961914,
            "volume": 228966900
        },
        {
            "date": "2025-04-16",
            "open": 104.52537649088836,
            "high": 106.76484672728219,
            "low": 100.4263361362673,
            "close": 104.46538543701172,
            "volume": 397016900
        },
        {
            "date": "2025-04-17",
            "open": 104.4253812132841,
            "high": 104.44538077133734,
            "low": 100.02642426353728,
            "close": 101.46607971191406,
            "volume": 292517500
        },
        {
            "date": "2025-04-21",
            "open": 98.74673137333838,
            "high": 99.41657935183265,
            "low": 95.01761424618036,
            "close": 96.88717651367188,
            "volume": 288501100
        },
        {
            "date": "2025-04-22",
            "open": 98.75672452641882,
            "high": 99.78648062043173,
            "low": 97.2570779520085,
            "close": 98.86669921875,
            "volume": 241004800
        },
        {
            "date": "2025-04-23",
            "open": 104.49537749742674,
            "high": 104.77531795205407,
            "low": 101.99596635952085,
            "close": 102.68580627441406,
            "volume": 247526000
        },
        {
            "date": "2025-04-24",
            "open": 103.45562063709751,
            "high": 106.51489717654988,
            "low": 103.08570507328525,
            "close": 106.40492248535156,
            "volume": 220815000
        },
        {
            "date": "2025-04-25",
            "open": 106.82483233532861,
            "high": 111.8936379045766,
            "low": 105.70510100806126,
            "close": 110.98385620117188,
            "volume": 251064700
        },
        {
            "date": "2025-04-28",
            "open": 109.66416443154382,
            "high": 110.34400455936343,
            "low": 105.9950231207954,
            "close": 108.70439147949219,
            "volume": 207708500
        },
        {
            "date": "2025-04-29",
            "open": 107.64462809509338,
            "high": 110.1740307356611,
            "low": 107.41468656100368,
            "close": 108.99430847167969,
            "volume": 170444300
        },
        {
            "date": "2025-04-30",
            "open": 104.44538450923935,
            "high": 108.89433288574219,
            "low": 104.05547701680861,
            "close": 108.89433288574219,
            "volume": 235044600
        },
        {
            "date": "2025-05-01",
            "open": 113.05335693358144,
            "high": 114.91291927434723,
            "low": 111.27377757314032,
            "close": 111.58370208740234,
            "volume": 236121500
        },
        {
            "date": "2025-05-02",
            "open": 114.15310576985596,
            "high": 115.37281962529518,
            "low": 113.34329900218786,
            "close": 114.47303009033203,
            "volume": 190194800
        },
        {
            "date": "2025-05-05",
            "open": 112.88340074602954,
            "high": 114.64298057759626,
            "low": 112.63345964895049,
            "close": 113.79318237304688,
            "volume": 133163200
        },
        {
            "date": "2025-05-06",
            "open": 111.4537475013017,
            "high": 114.7129742117387,
            "low": 110.7938992837595,
            "close": 113.51325988769531,
            "volume": 158525600
        },
        {
            "date": "2025-05-07",
            "open": 113.02337494499027,
            "high": 117.65228163619798,
            "low": 112.25355204144066,
            "close": 117.03242492675781,
            "volume": 206758800
        },
        {
            "date": "2025-05-08",
            "open": 118.22215145930612,
            "high": 118.65205049698933,
            "low": 115.82271514729747,
            "close": 117.34236145019531,
            "volume": 198428100
        },
        {
            "date": "2025-05-09",
            "open": 117.32235248570746,
            "high": 118.20215005190205,
            "low": 115.18285724943865,
            "close": 116.62252044677734,
            "volume": 132972200
        },
        {
            "date": "2025-05-12",
            "open": 121.94126742822685,
            "high": 122.97102355957031,
            "low": 120.25166311897564,
            "close": 122.97102355957031,
            "volume": 225023300
        },
        {
            "date": "2025-05-13",
            "open": 124.95056035306071,
            "high": 131.18908818741485,
            "low": 124.44067836400953,
            "close": 129.89938354492188,
            "volume": 330430100
        },
        {
            "date": "2025-05-14",
            "open": 133.16861033831793,
            "high": 135.40808800730593,
            "low": 131.6489642323906,
            "close": 135.30810546875,
            "volume": 281180800
        },
        {
            "date": "2025-05-15",
            "open": 134.258351724734,
            "high": 136.2678878895653,
            "low": 132.6287461607251,
            "close": 134.79823303222656,
            "volume": 226632600
        },
        {
            "date": "2025-05-16",
            "open": 136.18791721457987,
            "high": 136.31789147723805,
            "low": 133.42857277146337,
            "close": 135.36810302734375,
            "volume": 226542500
        },
        {
            "date": "2025-05-19",
            "open": 132.35879696756518,
            "high": 135.83797251007488,
            "low": 132.35879696756518,
            "close": 135.53805541992188,
            "volume": 193154600
        },
        {
            "date": "2025-05-20",
            "open": 134.2583525069389,
            "high": 134.54829272140586,
            "low": 132.58874781513978,
            "close": 134.3483428955078,
            "volume": 161514200
        },
        {
            "date": "2025-05-21",
            "open": 133.02864907239967,
            "high": 137.36762292180558,
            "low": 130.55922977564506,
            "close": 131.76895141601562,
            "volume": 270608700
        },
        {
            "date": "2025-05-22",
            "open": 132.19884131725317,
            "high": 134.21836966107523,
            "low": 131.51900885300861,
            "close": 132.7987060546875,
            "volume": 187344000
        },
        {
            "date": "2025-05-23",
            "open": 129.96937433382988,
            "high": 132.64873565144939,
            "low": 129.12957588399638,
            "close": 131.25906372070312,
            "volume": 198821300
        },
        {
            "date": "2025-05-27",
            "open": 134.1183754403962,
            "high": 135.6280293045703,
            "low": 133.27857708527512,
            "close": 135.4680633544922,
            "volume": 192953600
        },
        {
            "date": "2025-05-28",
            "open": 135.9979578766118,
            "high": 137.2176717346689,
            "low": 134.75824445795843,
            "close": 134.7782440185547,
            "volume": 304021100
        },
        {
            "date": "2025-05-29",
            "open": 142.21648797143945,
            "high": 143.45620133736625,
            "low": 137.87751407348716,
            "close": 139.15721130371094,
            "volume": 369241900
        },
        {
            "date": "2025-05-30",
            "open": 138.6873257641086,
            "high": 139.58710766728817,
            "low": 132.88868890141003,
            "close": 135.09817504882812,
            "volume": 333170900
        },
        {
            "date": "2025-06-02",
            "open": 135.45808684638126,
            "high": 138.08745689917103,
            "low": 135.36809645457458,
            "close": 137.34764099121094,
            "volume": 197663100
        },
        {
            "date": "2025-06-03",
            "open": 138.74729436292043,
            "high": 141.9665367692297,
            "low": 137.91748812723765,
            "close": 141.1867218017578,
            "volume": 225578800
        },
        {
            "date": "2025-06-04",
            "open": 142.15650682982962,
            "high": 142.3564566649135,
            "low": 139.5071219355859,
            "close": 141.88656616210938,
            "volume": 167120800
        },
        {
            "date": "2025-06-05",
            "open": 142.13651043477643,
            "high": 143.96608121416313,
            "low": 138.79730082341692,
            "close": 139.95703125,
            "volume": 231397900
        },
        {
            "date": "2025-06-06",
            "open": 142.47640682683559,
            "high": 143.23623746842864,
            "low": 141.47664251332282,
            "close": 141.6865997314453,
            "volume": 153986200
        },
        {
            "date": "2025-06-09",
            "open": 143.15627066728982,
            "high": 144.96584183837217,
            "low": 141.9065651342004,
            "close": 142.59640502929688,
            "volume": 185114500
        },
        {
            "date": "2025-06-10",
            "open": 142.65638139553192,
            "high": 144.25599524562207,
            "low": 141.4966510569608,
            "close": 143.92608642578125,
            "volume": 155881900
        },
        {
            "date": "2025-06-11",
            "open": 144.5859620448177,
            "high": 144.96590375929992,
            "low": 141.84641202362192,
            "close": 142.80625915527344,
            "volume": 167694000
        },
        {
            "date": "2025-06-12",
            "open": 141.94641106631286,
            "high": 144.9759063720703,
            "low": 141.82643588786814,
            "close": 144.9759063720703,
            "volume": 162365000
        },
        {
            "date": "2025-06-13",
            "open": 142.45632089769495,
            "high": 143.55614422146527,
            "low": 140.82660211679442,
            "close": 141.9464111328125,
            "volume": 180820600
        },
        {
            "date": "2025-06-16",
            "open": 143.32618096280035,
            "high": 146.1556971839991,
            "low": 143.1761967394354,
            "close": 144.66595458984375,
            "volume": 183133700
        },
        {
            "date": "2025-06-17",
            "open": 144.46598768948277,
            "high": 145.1958620737219,
            "low": 143.75609899624828,
            "close": 144.09603881835938,
            "volume": 139108000
        },
        {
            "date": "2025-06-18",
            "open": 143.9860537050978,
            "high": 145.62578045463974,
            "low": 143.0962022725339,
            "close": 145.455810546875,
            "volume": 161494100
        },
        {
            "date": "2025-06-20",
            "open": 145.42582047781178,
            "high": 146.17569581398777,
            "low": 142.6262828381709,
            "close": 143.8260955810547,
            "volume": 242956200
        },
        {
            "date": "2025-06-23",
            "open": 142.47632119978937,
            "high": 144.7559411184857,
            "low": 142.00639807778802,
            "close": 144.1460418701172,
            "volume": 154308900
        },
        {
            "date": "2025-06-24",
            "open": 145.53578955415,
            "high": 147.93539956519925,
            "low": 145.47580197371775,
            "close": 147.87539672851562,
            "volume": 187566100
        },
        {
            "date": "2025-06-25",
            "open": 149.24520677628502,
            "high": 154.4243389252029,
            "low": 149.23519867353343,
            "close": 154.28436279296875,
            "volume": 269146500
        },
        {
            "date": "2025-06-26",
            "open": 155.95406403411533,
            "high": 156.69394650127538,
            "low": 153.97439748110884,
            "close": 154.99423217773438,
            "volume": 198145700
        },
        {
            "date": "2025-06-27",
            "open": 156.01406285223712,
            "high": 158.68363258213975,
            "low": 155.23419369167684,
            "close": 157.72378540039062,
            "volume": 263234500
        },
        {
            "date": "2025-06-30",
            "open": 158.37368067249696,
            "high": 158.6336472456001,
            "low": 155.93409881773164,
            "close": 157.96376037597656,
            "volume": 194580300
        },
        {
            "date": "2025-07-01",
            "open": 156.26402965591922,
            "high": 157.17388214393176,
            "low": 151.46483925954294,
            "close": 153.2745361328125,
            "volume": 213143600
        },
        {
            "date": "2025-07-02",
            "open": 152.9545671877056,
            "high": 157.57380961936815,
            "low": 152.94457434216997,
            "close": 157.22386169433594,
            "volume": 171224100
        },
        {
            "date": "2025-07-03",
            "open": 158.34368228178877,
            "high": 160.95324924613055,
            "low": 157.74379112425564,
            "close": 159.3135223388672,
            "volume": 143716100
        },
        {
            "date": "2025-07-07",
            "open": 158.17371270193448,
            "high": 159.28352889047815,
            "low": 157.31385497697042,
            "close": 158.21371459960938,
            "volume": 140139000
        },
        {
            "date": "2025-07-08",
            "open": 159.3035323273478,
            "high": 160.19338386133896,
            "low": 158.36368604860908,
            "close": 159.97341918945312,
            "volume": 138133000
        },
        {
            "date": "2025-07-09",
            "open": 161.1932080055649,
            "high": 164.39267314506114,
            "low": 161.13322041798892,
            "close": 162.85293579101562,
            "volume": 183656400
        },
        {
            "date": "2025-07-10",
            "open": 164.29270331195812,
            "high": 164.4726660794993,
            "low": 161.5831469026993,
            "close": 164.07273864746094,
            "volume": 167704100
        },
        {
            "date": "2025-07-11",
            "open": 163.6927958392512,
            "high": 167.862101078866,
            "low": 163.44283738179527,
            "close": 164.89259338378906,
            "volume": 193633300
        },
        {
            "date": "2025-07-14",
            "open": 165.3425116109199,
            "high": 165.4625020418882,
            "low": 161.99307751467913,
            "close": 164.04273986816406,
            "volume": 136975800
        },
        {
            "date": "2025-07-15",
            "open": 171.1615549258278,
            "high": 172.37134531045626,
            "low": 169.17188012202328,
            "close": 170.671630859375,
            "volume": 230627400
        },
        {
            "date": "2025-07-16",
            "open": 171.03157616389174,
            "high": 171.72146396229547,
            "low": 168.87193138356372,
            "close": 171.34152221679688,
            "volume": 158831500
        },
        {
            "date": "2025-07-17",
            "open": 171.99141956059896,
            "high": 174.13106334471073,
            "low": 170.80161486292053,
            "close": 172.97125244140625,
            "volume": 160841100
        },
        {
            "date": "2025-07-18",
            "open": 173.61115431570738,
            "high": 174.22105359276725,
            "low": 171.23154479926822,
            "close": 172.38136291503906,
            "volume": 146456400
        },
        {
            "date": "2025-07-21",
            "open": 172.72129949000853,
            "high": 173.35119970444802,
            "low": 170.97159023323564,
            "close": 171.35153198242188,
            "volume": 123126100
        },
        {
            "date": "2025-07-22",
            "open": 171.31154005146294,
            "high": 171.36153479867312,
            "low": 164.55266825003173,
            "close": 167.00225830078125,
            "volume": 193114300
        },
        {
            "date": "2025-07-23",
            "open": 169.5018251648929,
            "high": 171.23153339032083,
            "low": 167.94208685699226,
            "close": 170.75161743164062,
            "volume": 154082200
        },
        {
            "date": "2025-07-24",
            "open": 172.41134882841166,
            "high": 173.80111724784433,
            "low": 171.27153886755505,
            "close": 173.7111358642578,
            "volume": 128984600
        },
        {
            "date": "2025-07-25",
            "open": 173.58115848322245,
            "high": 174.69097468726906,
            "low": 172.9312725713388,
            "close": 173.47117614746094,
            "volume": 122316800
        },
        {
            "date": "2025-07-28",
            "open": 173.99108478739527,
            "high": 176.97058528484683,
            "low": 173.94109004538618,
            "close": 176.7206268310547,
            "volume": 140023500
        },
        {
            "date": "2025-07-29",
            "open": 177.93044011853775,
            "high": 179.35020236643535,
            "low": 174.99092613442062,
            "close": 175.4808349609375,
            "volume": 154077500
        },
        {
            "date": "2025-07-30",
            "open": 176.48066791766442,
            "high": 179.86011122312902,
            "low": 176.01074478620916,
            "close": 179.24021911621094,
            "volume": 174312200
        },
        {
            "date": "2025-07-31",
            "open": 182.86960179799485,
            "high": 183.26954448460754,
            "low": 175.9007587673991,
            "close": 177.84043884277344,
            "volume": 221685400
        },
        {
            "date": "2025-08-01",
            "open": 174.06106522140865,
            "high": 176.51065501732398,
            "low": 170.86160006411595,
            "close": 173.69113159179688,
            "volume": 204529000
        },
        {
            "date": "2025-08-04",
            "open": 175.1309006070304,
            "high": 180.17005649193501,
            "low": 174.49100755408614,
            "close": 179.9700927734375,
            "volume": 148174600
        },
        {
            "date": "2025-08-05",
            "open": 179.59015184800575,
            "high": 180.23004490386853,
            "low": 175.87076869322405,
            "close": 178.23037719726562,
            "volume": 156407600
        },
        {
            "date": "2025-08-06",
            "open": 176.30069964693718,
            "high": 179.87009845787975,
            "low": 176.22071111043454,
            "close": 179.3901824951172,
            "volume": 137192300
        },
        {
            "date": "2025-08-07",
            "open": 181.53982980547644,
            "high": 183.84944343505214,
            "low": 178.77028591662776,
            "close": 180.73995971679688,
            "volume": 151878400
        },
        {
            "date": "2025-08-08",
            "open": 181.51982919208731,
            "high": 183.26953833968557,
            "low": 180.3700111699138,
            "close": 182.6696319580078,
            "volume": 123396700
        },
        {
            "date": "2025-08-11",
            "open": 182.01974653412333,
            "high": 183.80944232526838,
            "low": 180.2200426409657,
            "close": 182.0297393798828,
            "volume": 138323200
        },
        {
            "date": "2025-08-12",
            "open": 182.9295986692803,
            "high": 184.44933506001817,
            "low": 179.4301803710301,
            "close": 183.1295623779297,
            "volume": 145485700
        },
        {
            "date": "2025-08-13",
            "open": 182.5896420373941,
            "high": 183.93942375779682,
            "low": 179.3201965252013,
            "close": 181.559814453125,
            "volume": 179871700
        },
        {
            "date": "2025-08-14",
            "open": 179.72011917648817,
            "high": 182.98957985829236,
            "low": 179.43017409752198,
            "close": 181.98974609375,
            "volume": 129554000
        },
        {
            "date": "2025-08-15",
            "open": 181.84978375259033,
            "high": 181.86976944489334,
            "low": 178.01041021115256,
            "close": 180.42001342773438,
            "volume": 156602200
        },
        {
            "date": "2025-08-18",
            "open": 180.56999746834546,
            "high": 182.90960499065454,
            "low": 180.5599893659508,
            "close": 181.97975158691406,
            "volume": 132008000
        },
        {
            "date": "2025-08-19",
            "open": 182.39967416584764,
            "high": 182.46966985536903,
            "low": 175.46084035755914,
            "close": 175.61080932617188,
            "volume": 185229200
        },
        {
            "date": "2025-08-20",
            "open": 175.1408920976954,
            "high": 175.9707560164781,
            "low": 168.77195541250927,
            "close": 175.370849609375,
            "volume": 215142700
        },
        {
            "date": "2025-08-21",
            "open": 174.8209444570093,
            "high": 176.87059152353538,
            "low": 173.78110877087863,
            "close": 174.95091247558594,
            "volume": 140040900
        },
        {
            "date": "2025-08-22",
            "open": 172.58132291943235,
            "high": 178.56032512128596,
            "low": 171.17155351749952,
            "close": 177.96043395996094,
            "volume": 172789400
        },
        {
            "date": "2025-08-25",
            "open": 178.3203719824875,
            "high": 181.87977802218637,
            "low": 176.54066896263805,
            "close": 179.78012084960938,
            "volume": 163012800
        },
        {
            "date": "2025-08-26",
            "open": 180.03006938032237,
            "high": 182.35968393651802,
            "low": 178.7802771456414,
            "close": 181.7397918701172,
            "volume": 168688200
        },
        {
            "date": "2025-08-27",
            "open": 181.94975068857377,
            "high": 182.45967569067753,
            "low": 179.07023971825097,
            "close": 181.56982421875,
            "volume": 235518900
        },
        {
            "date": "2025-08-28",
            "open": 180.7899615720414,
            "high": 184.43934897141472,
            "low": 176.3806906932069,
            "close": 180.1400604248047,
            "volume": 281787800
        },
        {
            "date": "2025-08-29",
            "open": 178.08040158317536,
            "high": 178.12038822306508,
            "low": 173.12121914292007,
            "close": 174.1510467529297,
            "volume": 243257900
        },
        {
            "date": "2025-09-02",
            "open": 169.9717482776903,
            "high": 172.351357635579,
            "low": 167.19221149694363,
            "close": 170.75161743164062,
            "volume": 231164900
        },
        {
            "date": "2025-09-03",
            "open": 171.03158891427162,
            "high": 172.38137081666613,
            "low": 168.851958278929,
            "close": 170.59165954589844,
            "volume": 164424900
        },
        {
            "date": "2025-09-04",
            "open": 170.54166973363456,
            "high": 171.83144870716828,
            "low": 169.381858788342,
            "close": 171.63148498535156,
            "volume": 141670100
        },
        {
            "date": "2025-09-05",
            "open": 168.00209055003162,
            "high": 169.0019244592772,
            "low": 164.04275681292185,
            "close": 166.9922637939453,
            "volume": 224441400
        },
        {
            "date": "2025-09-08",
            "open": 167.5221599855096,
            "high": 170.93159698121408,
            "low": 167.32219627229085,
            "close": 168.2820281982422,
            "volume": 163769100
        },
        {
            "date": "2025-09-09",
            "open": 169.0618925540675,
            "high": 170.95157781434446,
            "low": 166.71229229208453,
            "close": 170.7316131591797,
            "volume": 157548400
        },
        {
            "date": "2025-09-10",
            "open": 176.61064931709572,
            "high": 179.26020289704138,
            "low": 175.44084555219968,
            "close": 177.300537109375,
            "volume": 226852000
        },
        {
            "date": "2025-09-11",
            "open": 179.66027757334626,
            "high": 180.26021784214308,
            "low": 176.4606317396978,
            "close": 177.1505584716797,
            "volume": 151159300
        },
        {
            "date": "2025-09-12",
            "open": 177.75047851465564,
            "high": 178.5803891806412,
            "low": 176.43061617633268,
            "close": 177.80047607421875,
            "volume": 124911000
        },
        {
            "date": "2025-09-15",
            "open": 175.65071055071581,
            "high": 178.830369337568,
            "low": 174.49083425075145,
            "close": 177.73048400878906,
            "volume": 147061600
        },
        {
            "date": "2025-09-16",
            "open": 176.98057174387853,
            "high": 177.4805168617991,
            "low": 174.36086420825131,
            "close": 174.86080932617188,
            "volume": 140737800
        },
        {
            "date": "2025-09-17",
            "open": 172.62104942275718,
            "high": 173.18098551277336,
            "low": 168.39151800406466,
            "close": 170.27130126953125,
            "volume": 211843800
        },
        {
            "date": "2025-09-18",
            "open": 173.96089569350613,
            "high": 177.08056354559588,
            "low": 172.94101865721873,
            "close": 176.2206573486328,
            "volume": 191763300
        },
        {
            "date": "2025-09-19",
            "open": 175.7506939671915,
            "high": 178.06043774665943,
            "low": 175.16074718989944,
            "close": 176.6505889892578,
            "volume": 237182100
        },
        {
            "date": "2025-09-22",
            "open": 175.28075846993005,
            "high": 184.52974299714734,
            "low": 174.69082690233378,
            "close": 183.58984375,
            "volume": 269637000
        },
        {
            "date": "2025-09-23",
            "open": 181.95002022927713,
            "high": 182.3999677661597,
            "low": 176.19065819152993,
            "close": 178.410400390625,
            "volume": 192559600
        },
        {
            "date": "2025-09-24",
            "open": 179.75025700209653,
            "high": 179.76025041106172,
            "low": 175.38072666046574,
            "close": 176.9505615234375,
            "volume": 143564100
        },
        {
            "date": "2025-09-25",
            "open": 174.4608472798892,
            "high": 180.2402117285651,
            "low": 173.11100459099512,
            "close": 177.67050170898438,
            "volume": 191586700
        },
        {
            "date": "2025-09-26",
            "open": 178.15043859744398,
            "high": 179.750269051669,
            "low": 174.91078879333958,
            "close": 178.17044067382812,
            "volume": 148573700
        },
        {
            "date": "2025-09-29",
            "open": 180.41019002973698,
            "high": 183.97980553666213,
            "low": 180.30021674934378,
            "close": 181.83004760742188,
            "volume": 193063500
        },
        {
            "date": "2025-09-30",
            "open": 182.06000352373024,
            "high": 187.32942897828707,
            "low": 181.4600633204032,
            "close": 186.55950927734375,
            "volume": 236981000
        },
        {
            "date": "2025-10-01",
            "open": 185.21967144700423,
            "high": 188.11934700723293,
            "low": 183.87980694521147,
            "close": 187.21945190429688,
            "volume": 173844900
        },
        {
            "date": "2025-10-02",
            "open": 189.57919146332628,
            "high": 191.0290292282152,
            "low": 188.03935198339767,
            "close": 188.8692626953125,
            "volume": 136805800
        },
        {
            "date": "2025-10-03",
            "open": 189.1692307003317,
            "high": 190.33910041164867,
            "low": 185.35965145286306,
            "close": 187.59939575195312,
            "volume": 137596900
        },
        {
            "date": "2025-10-06",
            "open": 185.4796339074747,
            "high": 187.20943969833962,
            "low": 183.3098739831843,
            "close": 185.51962280273438,
            "volume": 157678100
        },
        {
            "date": "2025-10-07",
            "open": 186.20955566811082,
            "high": 189.03924688644503,
            "low": 183.97980469837793,
            "close": 185.01968383789062,
            "volume": 140088000
        },
        {
            "date": "2025-10-08",
            "open": 186.5495190429729,
            "high": 189.57918508139647,
            "low": 186.51950830089396,
            "close": 189.0892333984375,
            "volume": 130168900
        },
        {
            "date": "2025-10-09",
            "open": 192.20888438710807,
            "high": 195.27855455286462,
            "low": 191.039014711271,
            "close": 192.54885864257812,
            "volume": 182997200
        },
        {
            "date": "2025-10-10",
            "open": 193.4887469873255,
            "high": 195.59851591827854,
            "low": 182.03001384654092,
            "close": 183.139892578125,
            "volume": 268774400
        },
        {
            "date": "2025-10-13",
            "open": 187.9493639887039,
            "high": 190.08912842775598,
            "low": 185.93959015922437,
            "close": 188.29933166503906,
            "volume": 153482800
        },
        {
            "date": "2025-10-14",
            "open": 184.74970821605342,
            "high": 184.77970370013514,
            "low": 179.6802578066599,
            "close": 180.01022338867188,
            "volume": 205641400
        },
        {
            "date": "2025-10-15",
            "open": 184.77971248532194,
            "high": 184.84969686580231,
            "low": 177.2705272995106,
            "close": 179.8102569580078,
            "volume": 214450500
        },
        {
            "date": "2025-10-16",
            "open": 182.20999112544493,
            "high": 183.2598789113643,
            "low": 179.75026972003684,
            "close": 181.7900390625,
            "volume": 179723300
        },
        {
            "date": "2025-10-17",
            "open": 180.1602152773484,
            "high": 184.07979842608083,
            "low": 179.7302697995737,
            "close": 183.19989013671875,
            "volume": 173135200
        },
        {
            "date": "2025-10-20",
            "open": 183.10990104163824,
            "high": 185.1796658652692,
            "low": 181.7100455780644,
            "close": 182.6199493408203,
            "volume": 128544700
        },
        {
            "date": "2025-10-21",
            "open": 182.76991679751694,
            "high": 182.76991679751694,
            "low": 179.7802549646251,
            "close": 181.14010620117188,
            "volume": 124240200
        },
        {
            "date": "2025-10-22",
            "open": 181.12011433169937,
            "high": 183.4198648953589,
            "low": 176.74059027394597,
            "close": 180.2602081298828,
            "volume": 162249600
        },
        {
            "date": "2025-10-23",
            "open": 180.4001849787377,
            "high": 183.0098989665471,
            "low": 179.7702492811968,
            "close": 182.13999938964844,
            "volume": 111363700
        },
        {
            "date": "2025-10-24",
            "open": 183.81980015643103,
            "high": 187.44940625639555,
            "low": 183.47984116964938,
            "close": 186.23953247070312,
            "volume": 131296700
        },
        {
            "date": "2025-10-27",
            "open": 189.9691435897376,
            "high": 191.97891738858848,
            "low": 188.4093020699799,
            "close": 191.46897888183594,
            "volume": 153452700
        },
        {
            "date": "2025-10-28",
            "open": 193.0288146936141,
            "high": 203.12769700573313,
            "low": 191.8889404255143,
            "close": 201.0079345703125,
            "volume": 297986200
        },
        {
            "date": "2025-10-29",
            "open": 207.95717223581016,
            "high": 212.1667169482571,
            "low": 204.7575264516481,
            "close": 207.01727294921875,
            "volume": 308829600
        },
        {
            "date": "2025-10-30",
            "open": 205.12746791137428,
            "high": 206.13736677538768,
            "low": 201.38788833732997,
            "close": 202.8677215576172,
            "volume": 178864400
        },
        {
            "date": "2025-10-31",
            "open": 206.42733011185774,
            "high": 207.94716749796044,
            "low": 202.04782138155986,
            "close": 202.4677734375,
            "volume": 179802200
        },
        {
            "date": "2025-11-03",
            "open": 208.05714970598171,
            "high": 211.31678618801203,
            "low": 205.53742218982754,
            "close": 206.85728454589844,
            "volume": 180267300
        },
        {
            "date": "2025-11-04",
            "open": 202.9777066091775,
            "high": 203.9476013046771,
            "low": 197.90825607143535,
            "close": 198.66818237304688,
            "volume": 188919300
        },
        {
            "date": "2025-11-05",
            "open": 198.7481902403631,
            "high": 202.89772869539195,
            "low": 194.6286320152979,
            "close": 195.18858337402344,
            "volume": 171350300
        },
        {
            "date": "2025-11-06",
            "open": 196.39843756369172,
            "high": 197.59830279082226,
            "low": 186.35954634625867,
            "close": 188.05935668945312,
            "volume": 223029800
        },
        {
            "date": "2025-11-07",
            "open": 184.87970536775757,
            "high": 188.29934352754728,
            "low": 178.8903723972709,
            "close": 188.1293487548828,
            "volume": 264942300
        },
        {
            "date": "2025-11-10",
            "open": 195.08858253564551,
            "high": 199.91805415635875,
            "low": 193.76872011438098,
            "close": 199.0281524658203,
            "volume": 198897100
        },
        {
            "date": "2025-11-11",
            "open": 195.13857433756354,
            "high": 195.3985402959953,
            "low": 191.2789975702345,
            "close": 193.1387939453125,
            "volume": 176483300
        },
        {
            "date": "2025-11-12",
            "open": 195.69851973704638,
            "high": 195.86849924763862,
            "low": 191.1090271797132,
            "close": 193.7787322998047,
            "volume": 154935300
        },
        {
            "date": "2025-11-13",
            "open": 191.02901978717685,
            "high": 191.4189763426968,
            "low": 183.82981362374773,
            "close": 186.8394775390625,
            "volume": 207423100
        },
        {
            "date": "2025-11-14",
            "open": 182.8399289693184,
            "high": 190.98902828114038,
            "low": 180.56018045425046,
            "close": 190.1491241455078,
            "volume": 186591900
        },
        {
            "date": "2025-11-17",
            "open": 185.9495778546046,
            "high": 188.9792438771453,
            "low": 184.29976516169708,
            "close": 186.5795135498047,
            "volume": 173628900
        },
        {
            "date": "2025-11-18",
            "open": 183.3598703733926,
            "high": 184.7797126313021,
            "low": 179.6302689297591,
            "close": 181.340087890625,
            "volume": 213598900
        },
        {
            "date": "2025-11-19",
            "open": 184.76969080502667,
            "high": 187.8393608341106,
            "low": 182.80991469001526,
            "close": 186.49951171875,
            "volume": 247246400
        },
        {
            "date": "2025-11-20",
            "open": 195.92847930218133,
            "high": 195.97847686300787,
            "low": 179.83025642841662,
            "close": 180.6201629638672,
            "volume": 343504800
        },
        {
            "date": "2025-11-21",
            "open": 181.22010834266524,
            "high": 184.5397359279593,
            "low": 172.91100782704066,
            "close": 178.86036682128906,
            "volume": 346926200
        },
        {
            "date": "2025-11-24",
            "open": 179.47030653663683,
            "high": 183.4798609481747,
            "low": 176.4606271183833,
            "close": 182.52996826171875,
            "volume": 256618300
        },
        {
            "date": "2025-11-25",
            "open": 174.89079203873564,
            "high": 178.14043506786686,
            "low": 169.53138015579162,
            "close": 177.80047607421875,
            "volume": 320600300
        },
        {
            "date": "2025-11-26",
            "open": 181.6100638206842,
            "high": 182.8899220695924,
            "low": 178.22043661727494,
            "close": 180.24020385742188,
            "volume": 183852000
        },
        {
            "date": "2025-11-28",
            "open": 178.99033405428943,
            "high": 179.2703020816569,
            "low": 176.48061521713345,
            "close": 176.98056030273438,
            "volume": 121332800
        },
        {
            "date": "2025-12-01",
            "open": 174.7408159055669,
            "high": 180.2802164760195,
            "low": 173.66093259662904,
            "close": 179.90025329589844,
            "volume": 188131000
        },
        {
            "date": "2025-12-02",
            "open": 181.7400335835938,
            "high": 185.63961443898967,
            "low": 179.98023235974816,
            "close": 181.44007873535156,
            "volume": 182632200
        },
        {
            "date": "2025-12-03",
            "open": 181.06012391136443,
            "high": 182.4299686383783,
            "low": 179.09033894604931,
            "close": 179.57028198242188,
            "volume": 165138000
        },
        {
            "date": "2025-12-04",
            "open": 181.61017209543593,
            "high": 184.51002440204854,
            "low": 179.95027347354184,
            "close": 183.37008666992188,
            "volume": 167364900
        },
        {
            "date": "2025-12-05",
            "open": 183.88004685245298,
            "high": 184.6500094505641,
            "low": 180.9002124089338,
            "close": 182.40013122558594,
            "volume": 143971100
        },
        {
            "date": "2025-12-08",
            "open": 182.6301165694494,
            "high": 187.98982714518382,
            "low": 182.39012406320575,
            "close": 185.5399627685547,
            "volume": 204378100
        },
        {
            "date": "2025-12-09",
            "open": 185.54995586495326,
            "high": 185.70995086836587,
            "low": 183.31008684903045,
            "close": 184.95999145507812,
            "volume": 144719700
        },
        {
            "date": "2025-12-10",
            "open": 184.9599880707457,
            "high": 185.46995496958337,
            "low": 182.03013874897007,
            "close": 183.77005004882812,
            "volume": 162785400
        },
        {
            "date": "2025-12-11",
            "open": 180.27023782951787,
            "high": 181.31019006496976,
            "low": 176.61043233199788,
            "close": 180.92019653320312,
            "volume": 182136600
        },
        {
            "date": "2025-12-12",
            "open": 181.10019518559332,
            "high": 182.81010931847595,
            "low": 174.61054106596097,
            "close": 175.01052856445312,
            "volume": 204274900
        },
        {
            "date": "2025-12-15",
            "open": 177.93037643785232,
            "high": 178.4103461991077,
            "low": 175.02053019793698,
            "close": 176.28045654296875,
            "volume": 164775600
        },
        {
            "date": "2025-12-16",
            "open": 176.25046044282257,
            "high": 178.48035080582065,
            "low": 174.8905333961456,
            "close": 177.71038818359375,
            "volume": 148588100
        },
        {
            "date": "2025-12-17",
            "open": 176.0904801521757,
            "high": 176.12047730871902,
            "low": 170.30078481189744,
            "close": 170.93075561523438,
            "volume": 222775500
        },
        {
            "date": "2025-12-18",
            "open": 174.52054772862792,
            "high": 176.14045512074784,
            "low": 171.8107030234881,
            "close": 174.1305694580078,
            "volume": 176096000
        },
        {
            "date": "2025-12-19",
            "open": 176.6604358481607,
            "high": 181.4401759084778,
            "low": 176.3304518785618,
            "close": 180.98020935058594,
            "volume": 324925900
        },
        {
            "date": "2025-12-22",
            "open": 183.91003698180788,
            "high": 184.15002947616998,
            "low": 182.34012994783166,
            "close": 183.6800537109375,
            "volume": 129064400
        },
        {
            "date": "2025-12-23",
            "open": 182.96010023623109,
            "high": 189.31975669034466,
            "low": 182.89009670029142,
            "close": 189.19976806640625,
            "volume": 174873600
        },
        {
            "date": "2025-12-24",
            "open": 187.92983057380172,
            "high": 188.899779295176,
            "low": 186.57989753660073,
            "close": 188.59979248046875,
            "volume": 65528500
        },
        {
            "date": "2025-12-26",
            "open": 189.9097162518428,
            "high": 192.67957056140054,
            "low": 187.98982202804387,
            "close": 190.51968383789062,
            "volume": 139740300
        },
        {
            "date": "2025-12-29",
            "open": 187.6998414610299,
            "high": 188.749772392931,
            "low": 185.8999358866866,
            "close": 188.20980834960938,
            "volume": 120006100
        },
        {
            "date": "2025-12-30",
            "open": 188.22982052336855,
            "high": 188.9797799436452,
            "low": 186.91987858592935,
            "close": 187.52984619140625,
            "volume": 97687300
        },
        {
            "date": "2025-12-31",
            "open": 189.55975523635485,
            "high": 190.54969193131708,
            "low": 186.47991997410415,
            "close": 186.4899139404297,
            "volume": 120100500
        },
        {
            "date": "2026-01-02",
            "open": 189.82971935613102,
            "high": 192.91954841717475,
            "low": 188.24980305842183,
            "close": 188.83978271484375,
            "volume": 148240500
        },
        {
            "date": "2026-01-05",
            "open": 191.74961996436147,
            "high": 193.61952916959007,
            "low": 186.13992286460274,
            "close": 188.1098175048828,
            "volume": 183529700
        },
        {
            "date": "2026-01-06",
            "open": 190.50969495089785,
            "high": 192.15959956375178,
            "low": 186.80989821500853,
            "close": 187.22987365722656,
            "volume": 176862600
        },
        {
            "date": "2026-01-07",
            "open": 188.55979791265688,
            "high": 191.35963411085106,
            "low": 186.54989697142676,
            "close": 189.09976196289062,
            "volume": 153543200
        },
        {
            "date": "2026-01-08",
            "open": 189.09977067708235,
            "high": 189.53974931649188,
            "low": 183.70006889406122,
            "close": 185.0299835205078,
            "volume": 172457000
        },
        {
            "date": "2026-01-09",
            "open": 185.06998015284367,
            "high": 186.32990643372668,
            "low": 183.66005283935564,
            "close": 184.84999084472656,
            "volume": 131327500
        },
        {
            "date": "2026-01-12",
            "open": 183.2100845491025,
            "high": 187.10986736077922,
            "low": 183.010098425574,
            "close": 184.92999267578125,
            "volume": 137968500
        },
        {
            "date": "2026-01-13",
            "open": 184.9899882929175,
            "high": 188.0998205983224,
            "low": 183.3900687774691,
            "close": 185.79994201660156,
            "volume": 160128900
        },
        {
            "date": "2026-01-14",
            "open": 184.3100252062831,
            "high": 184.45001701406107,
            "low": 180.79021156477043,
            "close": 183.1300811767578,
            "volume": 159586100
        },
        {
            "date": "2026-01-15",
            "open": 186.48991316970114,
            "high": 189.6897370464893,
            "low": 186.31992419508657,
            "close": 187.03988647460938,
            "volume": 206188600
        },
        {
            "date": "2026-01-16",
            "open": 189.06976141755646,
            "high": 190.4296883714215,
            "low": 186.06992389502736,
            "close": 186.21990966796875,
            "volume": 187967200
        },
        {
            "date": "2026-01-20",
            "open": 181.89014292514364,
            "high": 182.37012791600927,
            "low": 177.60038196777572,
            "close": 178.06036376953125,
            "volume": 223345300
        },
        {
            "date": "2026-01-21",
            "open": 179.04031586008543,
            "high": 185.3699752173061,
            "low": 178.3903418724365,
            "close": 183.31008911132812,
            "volume": 200381000
        },
        {
            "date": "2026-01-22",
            "open": 184.7399951080077,
            "high": 186.15991637882954,
            "low": 183.92003219020145,
            "close": 184.82998657226562,
            "volume": 139636600
        },
        {
            "date": "2026-01-23",
            "open": 187.48984685190618,
            "high": 189.58973923983262,
            "low": 186.80989099781206,
            "close": 187.6598358154297,
            "volume": 142748100
        },
        {
            "date": "2026-01-26",
            "open": 187.1498802806874,
            "high": 189.1097657209082,
            "low": 185.97994539629804,
            "close": 186.4599151611328,
            "volume": 124799600
        },
        {
            "date": "2026-01-27",
            "open": 187.22986667366473,
            "high": 189.9897117301412,
            "low": 185.6899415183402,
            "close": 188.50979614257812,
            "volume": 143711600
        },
        {
            "date": "2026-01-28",
            "open": 191.25965707901594,
            "high": 192.33960048487265,
            "low": 189.82972650403363,
            "close": 191.5096435546875,
            "volume": 148552700
        },
        {
            "date": "2026-01-29",
            "open": 191.32963792417547,
            "high": 193.46952146246272,
            "low": 186.04992498376654,
            "close": 192.49957275390625,
            "volume": 171764400
        },
        {
            "date": "2026-01-30",
            "open": 191.19965692455457,
            "high": 194.47947816452233,
            "low": 189.45974561417185,
            "close": 191.11965942382812,
            "volume": 179489500
        },
        {
            "date": "2026-02-02",
            "open": 187.1898706566695,
            "high": 190.2897090701948,
            "low": 184.87000408758857,
            "close": 185.59996032714844,
            "volume": 165794100
        },
        {
            "date": "2026-02-03",
            "open": 186.22992037566058,
            "high": 186.25991753048794,
            "low": 176.22045266395375,
            "close": 180.33023071289062,
            "volume": 204019600
        },
        {
            "date": "2026-02-04",
            "open": 179.45029148582987,
            "high": 179.57028010697434,
            "low": 171.90069716024271,
            "close": 174.18057250976562,
            "volume": 207014100
        },
        {
            "date": "2026-02-05",
            "open": 174.92051964769362,
            "high": 176.81043194569037,
            "low": 171.020736948564,
            "close": 171.87069702148438,
            "volume": 206312900
        },
        {
            "date": "2026-02-06",
            "open": 176.6804343618602,
            "high": 186.98987361565233,
            "low": 174.59055120100808,
            "close": 185.39996337890625,
            "volume": 231346200
        },
        {
            "date": "2026-02-09",
            "open": 184.25002288009932,
            "high": 193.64952333361757,
            "low": 183.9400420976916,
            "close": 190.0297088623047,
            "volume": 196387400
        },
        {
            "date": "2026-02-10",
            "open": 191.36964298604585,
            "high": 192.46957427391544,
            "low": 188.10980972728564,
            "close": 188.52978515625,
            "volume": 136764800
        },
        {
            "date": "2026-02-11",
            "open": 192.43958265041238,
            "high": 193.24953637655122,
            "low": 188.75978911487715,
            "close": 190.0397186279297,
            "volume": 144192700
        },
        {
            "date": "2026-02-12",
            "open": 193.01955263160718,
            "high": 193.5995230748733,
            "low": 186.49990120030046,
            "close": 186.9298858642578,
            "volume": 189932500
        },
        {
            "date": "2026-02-13",
            "open": 187.4698554447334,
            "high": 187.4898586352177,
            "low": 181.58017462912434,
            "close": 182.80010986328125,
            "volume": 161888000
        },
        {
            "date": "2026-02-17",
            "open": 181.74016448672575,
            "high": 187.13986615921206,
            "low": 179.17029624003743,
            "close": 184.95999145507812,
            "volume": 162276900
        },
        {
            "date": "2026-02-18",
            "open": 188.73978069812654,
            "high": 190.3596881055438,
            "low": 186.7498829478333,
            "close": 187.96981811523438,
            "volume": 164749100
        },
        {
            "date": "2026-02-19",
            "open": 187.04988063530703,
            "high": 188.41980165789556,
            "low": 185.64996245587088,
            "close": 187.88983154296875,
            "volume": 126554500
        },
        {
            "date": "2026-02-20",
            "open": 186.5599139825128,
            "high": 190.31970507557438,
            "low": 185.92994318264132,
            "close": 189.8097381591797,
            "volume": 178422300
        },
        {
            "date": "2026-02-23",
            "open": 191.3896412925324,
            "high": 193.93950641757905,
            "low": 189.56974766836524,
            "close": 191.53964233398438,
            "volume": 171584800
        },
        {
            "date": "2026-02-24",
            "open": 191.47964208446245,
            "high": 193.75951747058733,
            "low": 187.38985183856119,
            "close": 192.83956909179688,
            "volume": 175123600
        },
        {
            "date": "2026-02-25",
            "open": 194.43946745531196,
            "high": 197.61930319203404,
            "low": 193.77949953248776,
            "close": 195.54940795898438,
            "volume": 250637100
        },
        {
            "date": "2026-02-26",
            "open": 194.25948668244985,
            "high": 194.27947461393586,
            "low": 184.31002841741252,
            "close": 184.87998962402344,
            "volume": 360807900
        },
        {
            "date": "2026-02-27",
            "open": 181.2401979138715,
            "high": 182.5801217841234,
            "low": 176.3704661683341,
            "close": 177.180419921875,
            "volume": 311636500
        },
        {
            "date": "2026-03-02",
            "open": 175.00052620838028,
            "high": 183.45008125730604,
            "low": 174.63055110847353,
            "close": 182.47012329101562,
            "volume": 209095300
        },
        {
            "date": "2026-03-03",
            "open": 178.4803396065267,
            "high": 180.8901975001603,
            "low": 176.91041730394699,
            "close": 180.04025268554688,
            "volume": 178099400
        },
        {
            "date": "2026-03-04",
            "open": 180.4302401537762,
            "high": 184.69000418349444,
            "low": 180.0502558302461,
            "close": 183.03009033203125,
            "volume": 177731200
        },
        {
            "date": "2026-03-05",
            "open": 181.1601973472636,
            "high": 184.05004039552568,
            "low": 177.87038204113773,
            "close": 183.330078125,
            "volume": 198779700
        },
        {
            "date": "2026-03-06",
            "open": 179.83025866705609,
            "high": 182.7500987288974,
            "low": 176.81043317462274,
            "close": 177.8103790283203,
            "volume": 189021900
        },
        {
            "date": "2026-03-09",
            "open": 176.82042919903367,
            "high": 182.90010189125664,
            "low": 175.55049367782217,
            "close": 182.64010620117188,
            "volume": 177213600
        },
        {
            "date": "2026-03-10",
            "open": 182.39012758732315,
            "high": 186.42991760168223,
            "low": 182.00014929336922,
            "close": 184.760009765625,
            "volume": 179118500
        },
        {
            "date": "2026-03-11",
            "open": 185.91000366210938,
            "high": 187.6199951171875,
            "low": 184.4499969482422,
            "close": 186.02999877929688,
            "volume": 145280400
        },
        {
            "date": "2026-03-12",
            "open": 184.0500030517578,
            "high": 184.94000244140625,
            "low": 181.75,
            "close": 183.13999938964844,
            "volume": 155762700
        },
        {
            "date": "2026-03-13",
            "open": 184.9199981689453,
            "high": 186.08999633789062,
            "low": 179.94000244140625,
            "close": 180.25,
            "volume": 160988400
        },
        {
            "date": "2026-03-16",
            "open": 182.97000122070312,
            "high": 188.8800048828125,
            "low": 181.41000366210938,
            "close": 183.22000122070312,
            "volume": 217307400
        },
        {
            "date": "2026-03-17",
            "open": 185.05999755859375,
            "high": 185.39999389648438,
            "low": 181.67999267578125,
            "close": 181.92999267578125,
            "volume": 182497800
        },
        {
            "date": "2026-03-18",
            "open": 182.47999572753906,
            "high": 183.3800048828125,
            "low": 180.3300018310547,
            "close": 180.39999389648438,
            "volume": 156683100
        },
        {
            "date": "2026-03-19",
            "open": 178.00999450683594,
            "high": 179.97999572753906,
            "low": 175.7899932861328,
            "close": 178.55999755859375,
            "volume": 170968500
        },
        {
            "date": "2026-03-20",
            "open": 178.0,
            "high": 178.25999450683594,
            "low": 171.72000122070312,
            "close": 172.6999969482422,
            "volume": 241323500
        },
        {
            "date": "2026-03-23",
            "open": 177.25999450683594,
            "high": 178.3699951171875,
            "low": 174.75999450683594,
            "close": 175.63999938964844,
            "volume": 182836300
        },
        {
            "date": "2026-03-24",
            "open": 174.8300018310547,
            "high": 176.22000122070312,
            "low": 173.97999572753906,
            "close": 175.1999969482422,
            "volume": 147667800
        },
        {
            "date": "2026-03-25",
            "open": 177.10000610351562,
            "high": 181.22000122070312,
            "low": 176.85000610351562,
            "close": 178.67999267578125,
            "volume": 162602100
        },
        {
            "date": "2026-03-26",
            "open": 176.07000732421875,
            "high": 176.50999450683594,
            "low": 171.13999938964844,
            "close": 171.24000549316406,
            "volume": 186152200
        },
        {
            "date": "2026-03-27",
            "open": 170.0,
            "high": 170.97000122070312,
            "low": 167.00999450683594,
            "close": 167.52000427246094,
            "volume": 196212700
        },
        {
            "date": "2026-03-30",
            "open": 168.77999877929688,
            "high": 169.4499969482422,
            "low": 164.27000427246094,
            "close": 165.1699981689453,
            "volume": 184702300
        }
    ]
}